breezeway/__init__.py
breezeway/breezeway_client.py
breezeway/errors.py
breezeway/models/__init__.py
breezeway/models/auth.py
breezeway/models/base.py
breezeway/models/company.py
breezeway/models/reservation.py
breezeway/models/task.py
breezeway/models/unit.py
breezeway/models/user.py
breezeway/resources/__init__.py
breezeway/resources/base.py
breezeway/resources/company.py
breezeway/resources/reservation.py
breezeway/resources/unit.py
breezeway/resources/user.py
breezeway-0.1.0a2.dist-info/METADATA
breezeway-0.1.0a2.dist-info/WHEEL
breezeway-0.1.0a2.dist-info/licenses/LICENSE.txt
breezeway-0.1.0a2.dist-info/RECORD
