Metadata-Version: 2.4
Name: breezeway
Version: 0.1.0a2
Summary: Library for interacting with Breezeway's API.
License: MIT
License-File: LICENSE.txt
Author: Anthony DeGarimore
Author-email: anthony@pasoroblesconcierge.com
Maintainer: Anthony DeGarimore
Maintainer-email: anthony@pasoroblesconcierge.com
Requires-Python: >=3.13
Classifier: License :: OSI Approved :: MIT License
Classifier: Programming Language :: Python :: 3
Classifier: Programming Language :: Python :: 3.13
Classifier: Programming Language :: Python :: 3.14
Provides-Extra: dev
Requires-Dist: httpx (>=0.28.1)
Requires-Dist: pydantic (>=2.12.5)
Requires-Dist: pytest ; extra == "dev"
Project-URL: Bug Tracker, https://github.com/Paso-Robles-Vacation-Rentals/breezeway-python/issues
Project-URL: Repository, https://github.com/Paso-Robles-Vacation-Rentals/breezeway-python
